k8sgen/APIResources.py
k8sgen/Components.py
k8sgen/__init__.py
k8sgen/base.py
k8sgen/builder.py
k8sgen/data_file.py
k8sgen/utils.py
k8sgen/data/apiresources.txt
k8sgen/data/components.txt
k8sgen/data/APIResources/APIService.json
k8sgen/data/APIResources/Binding.json
k8sgen/data/APIResources/CSIDriver.json
k8sgen/data/APIResources/CSINode.json
k8sgen/data/APIResources/CertificateSigningRequest.json
k8sgen/data/APIResources/ClusterRole.json
k8sgen/data/APIResources/ClusterRoleBinding.json
k8sgen/data/APIResources/ComponentStatus.json
k8sgen/data/APIResources/ConfigMap.json
k8sgen/data/APIResources/ControllerRevision.json
k8sgen/data/APIResources/CronJob.json
k8sgen/data/APIResources/CustomResourceDefinition.json
k8sgen/data/APIResources/DaemonSet.json
k8sgen/data/APIResources/Deployment.json
k8sgen/data/APIResources/EndpointSlice.json
k8sgen/data/APIResources/Endpoints.json
k8sgen/data/APIResources/Event.json
k8sgen/data/APIResources/HorizontalPodAutoscaler.json
k8sgen/data/APIResources/Ingress.json
k8sgen/data/APIResources/IngressClass.json
k8sgen/data/APIResources/Job.json
k8sgen/data/APIResources/Lease.json
k8sgen/data/APIResources/LimitRange.json
k8sgen/data/APIResources/LocalSubjectAccessReview.json
k8sgen/data/APIResources/MutatingWebhookConfiguration.json
k8sgen/data/APIResources/Namespace.json
k8sgen/data/APIResources/NetworkPolicy.json
k8sgen/data/APIResources/Node.json
k8sgen/data/APIResources/PersistentVolume.json
k8sgen/data/APIResources/PersistentVolumeClaim.json
k8sgen/data/APIResources/Pod.json
k8sgen/data/APIResources/PodDisruptionBudget.json
k8sgen/data/APIResources/PodSecurityPolicy.json
k8sgen/data/APIResources/PodTemplate.json
k8sgen/data/APIResources/PriorityClass.json
k8sgen/data/APIResources/ReplicaSet.json
k8sgen/data/APIResources/ReplicationController.json
k8sgen/data/APIResources/ResourceQuota.json
k8sgen/data/APIResources/Role.json
k8sgen/data/APIResources/RoleBinding.json
k8sgen/data/APIResources/RuntimeClass.json
k8sgen-1.1.2.dist-info/LICENSE
k8sgen-1.1.2.dist-info/METADATA
k8sgen-1.1.2.dist-info/WHEEL
k8sgen-1.1.2.dist-info/top_level.txt
k8sgen-1.1.2.dist-info/RECORD
