Metadata-Version: 2.1
Name: k8sgen
Version: 1.1.2
Summary: A Python package to enable dynamic generation of Kubernetes manifests
Home-page: https://github.com/jfcarter2358/k8sGen
Author: John Carter
Author-email: jfcarter2358@gmail.com
License: MIT
Platform: UNKNOWN
Classifier: Programming Language :: Python :: 3
Classifier: License :: OSI Approved :: MIT License
Classifier: Operating System :: OS Independent
Requires-Python: >=3.7
